{"version":1,"resource":"vscode-remote://ssh-remote%2B7b22686f73744e616d65223a226c6f63616c686f7374222c2275736572223a226f646f6f222c22706f7274223a323232327d/var/lib/odoo/modules/dungeons/views/building_view.xml","entries":[{"id":"0yZz.xml","timestamp":1666090698833},{"id":"Nrkg.xml","timestamp":1666090773221},{"id":"K1os.xml","timestamp":1666105513419},{"id":"irJB.xml","timestamp":1666105767111},{"id":"DDSi.xml","timestamp":1666105801063},{"id":"o16e.xml","timestamp":1666105880417},{"id":"nVzA.xml","timestamp":1666105938188},{"id":"xJoA.xml","timestamp":1666105995363},{"id":"o5qm.xml","timestamp":1666106054986},{"id":"eCvR.xml","timestamp":1666106109477},{"id":"ePyy.xml","timestamp":1666106171236},{"id":"SoYR.xml","timestamp":1666106331229},{"id":"xo9D.xml","timestamp":1666106357349},{"id":"CgrU.xml","source":"undoRedo.source","timestamp":1666106420055},{"id":"k4OQ.xml","timestamp":1666106426735},{"id":"dw9c.xml","timestamp":1666106496834}]}